{
  "companies": [],
  "entries": [
    {
      "id": 1,
      "type": "expense",
      "payments": [],
      "entity": "personal",
      "date": "2026-03-22",
      "amount": 1000,
      "category": "Food & Dining",
      "description": "",
      "payMethod": "UPI / GPay",
      "notes": ""
    },
    {
      "id": 2,
      "type": "expense",
      "payments": [],
      "entity": "personal",
      "date": "2026-03-22",
      "amount": 2000,
      "category": "Food & Dining",
      "description": "",
      "payMethod": "UPI / GPay",
      "notes": ""
    },
    {
      "id": 3,
      "type": "expense",
      "payments": [],
      "entity": "personal",
      "date": "2026-03-23",
      "amount": 1000000,
      "category": "Food & Dining",
      "description": "",
      "payMethod": "UPI / GPay",
      "notes": ""
    }
  ],
  "profile": {
    "name": "",
    "joined": "2026-03-22"
  },
  "settings": {
    "theme": "light",
    "monthlyBudget": 0
  },
  "_version": "22.5",
  "_lastSaved": "2026-03-23T06:50:27.666Z"
}